test_platform_helper/__init__.py
test_platform_helper/utils.py
test_platform_helper/config_helper/__init__.py
test_platform_helper/config_helper/nacos.py
test_platform_helper/http3_helper/__init__.py
test_platform_helper/http3_helper/aioquic.py
test_platform_helper-0.0.5.dist-info/LICENSE
test_platform_helper-0.0.5.dist-info/METADATA
test_platform_helper-0.0.5.dist-info/WHEEL
test_platform_helper-0.0.5.dist-info/top_level.txt
test_platform_helper-0.0.5.dist-info/RECORD
