Metadata-Version: 2.1
Name: test-platform-helper
Version: 0.0.5
Summary: test platform backend helper package
Home-page: UNKNOWN
Author: chenxu.tian
Author-email: 472159011@qq.com
License: UNKNOWN
Keywords: Sanic
Platform: UNKNOWN
Classifier: Programming Language :: Python :: 3
Requires-Python: >=3.7
Requires-Dist: httpx
Requires-Dist: sanic[ext]
Requires-Dist: aioquic
Requires-Dist: wsproto
